MANIFEST.in
account_chart.xml
account_tax.xml
account_types.xml
l10n_hn_base.xml
setup.py
./__init__.py
./__openerp__.py
i18n/ca.po
i18n/es.po
i18n/es_CR.po
i18n/es_PY.po
i18n/fr.po
i18n/gl.po
i18n/hu.po
i18n/it.po
i18n/l10n_hn.pot
i18n/nl.po
i18n/pt.po
i18n/pt_BR.po
i18n/sl.po
i18n/sr@latin.po
i18n/tr.po
openerp_l10n_hn.egg-info/PKG-INFO
openerp_l10n_hn.egg-info/SOURCES.txt
openerp_l10n_hn.egg-info/dependency_links.txt
openerp_l10n_hn.egg-info/requires.txt
openerp_l10n_hn.egg-info/top_level.txt
static/src/img/icon.png